Metadata-Version: 1.0
Name: eveauth
Version: 0.0.3
Summary: A library for working with the EVE Online SSO.
Home-page: https://github.com/regner/eveauth
Author: UNKNOWN
Author-email: UNKNOWN
License: UNKNOWN
Platform: UNKNOWN
